{
  "game_id": "stw-001",
  "game_template_name": "spin-the-wheel",
  "name": "Spin the Wheel",
  "merchant_id": "merchant-demo",
  "game_background_image": "",
  "game_logo_image": "",
  "start_date": "2024-01-01T00:00:00.000Z",
  "end_date": "2024-12-31T23:59:59.000Z",
  "status": "created",
  "is_active": true,
  "hard_play_count_limit": 0,
  "play_count": 0,
  "prizes": {},
  "is_quests_enabled": false,
  "quests": [],
  "leaderboard_id": null,
  "prize_distribution_strategy": "cascade",
  "createdAt": "2024-01-01T00:00:00.000Z",
  "updatedAt": "2024-01-01T00:00:00.000Z",
  "__v": 0,
  "options": [
    {
      "input_name": "title",
      "input_type": "string",
      "value": "Spin the Wheel",
      "required": true
    },
    {
      "input_name": "description",
      "input_type": "string",
      "value": "Players spin the wheel once per eligible session to receive a random reward.",
      "required": true
    },
    {
      "input_name": "wheelImage",
      "input_type": "image",
      "value": "/images/stw-game-assets/wheel.png",
      "required": true
    },
    {
      "input_name": "pointerImage",
      "input_type": "image",
      "value": "/images/stw-game-assets/pointer.png",
      "required": true
    },
    {
      "input_name": "backgroundImage",
      "input_type": "image",
      "value": "/images/stw-game-assets/background.png",
      "required": true
    },
    {
      "input_name": "spinButtonImage",
      "input_type": "image",
      "value": "/images/stw-game-assets/spin-button.png",
      "required": true
    },
    {
      "input_name": "maxSpinsPerUser",
      "input_type": "number",
      "value": "1",
      "required": true
    },
    {
      "input_name": "spinCooldownSeconds",
      "input_type": "number",
      "value": "86400",
      "required": true
    },
    {
      "input_name": "submissionEndpoint",
      "input_type": "string",
      "value": "/api/games/spin-the-wheel/stw-001/results",
      "required": true
    },
    {
      "input_name": "prizeSegments",
      "input_type": "string",
      "value": "[{\"id\": \"voucher-5\", \"label\": \"$5 Voucher\", \"probability\": 0.2, \"image\": \"/images/stw-game-assets/segments/voucher-5.png\", \"description\": \"Discount on next purchase\"}, {\"id\": \"voucher-10\", \"label\": \"$10 Voucher\", \"probability\": 0.1, \"image\": \"/images/stw-game-assets/segments/voucher-10.png\", \"description\": \"Premium discount reward\"}, {\"id\": \"free-shipping\", \"label\": \"Free Shipping\", \"probability\": 0.3, \"image\": \"/images/stw-game-assets/segments/free-shipping.png\", \"description\": \"Waive delivery fees\"}, {\"id\": \"try-again\", \"label\": \"Try Again\", \"probability\": 0.4, \"image\": \"/images/stw-game-assets/segments/try-again.png\", \"description\": \"No reward\"}]",
      "required": true
    }
  ]
}
